topsis/__init__.py
topsis/topsis.py
topsis_101703382-0.0.2.data/scripts/topsis-101703382_cli
topsis_101703382-0.0.2.dist-info/LICENSE.txt
topsis_101703382-0.0.2.dist-info/METADATA
topsis_101703382-0.0.2.dist-info/WHEEL
topsis_101703382-0.0.2.dist-info/top_level.txt
topsis_101703382-0.0.2.dist-info/RECORD
