Metadata-Version: 2.1
Name: topsis-101703382
Version: 0.0.2
Summary: Automatic topsis for decision making
Home-page: https://github.com/Paras1598/Topsis
Author: Paras Arora
Author-email: parora_be17@thapar.edu
License: UNKNOWN
Keywords: command-line,topsis-python,TOPSIS
Platform: UNKNOWN
Classifier: Programming Language :: Python :: 3
Classifier: License :: OSI Approved :: MIT License
Classifier: Operating System :: OS Independent
Requires-Python: >=3.6
Requires-Dist: numpy
Requires-Dist: pandas
